data_handler/__init__.py
data_handler/benchmark.py
data_handler/conversion.py
data_handler/ffmpeg_utils.py
data_handler/modifications.py
data_handler/split.py
data_handler/utils.py
data_handler-1.0.0.dist-info/LICENSE
data_handler-1.0.0.dist-info/METADATA
data_handler-1.0.0.dist-info/WHEEL
data_handler-1.0.0.dist-info/top_level.txt
data_handler-1.0.0.dist-info/RECORD
