Metadata-Version: 2.1
Name: data-handler
Version: 1.0.0
Summary: A package for handling and structuring of data before training.
Home-page: https://github.com/vardanagarwal/data_handling
Author: Vardan Agarwal
Author-email: vardanagarwal16@gmail.com
Project-URL: Bug Tracker, https://github.com/vardanagarwal/data_handling/issues
Classifier: Programming Language :: Python :: 3
Classifier: License :: OSI Approved :: MIT License
Classifier: Operating System :: OS Independent
Requires-Python: >=3.7
License-File: LICENSE
Requires-Dist: albumentations
Requires-Dist: matplotlib
Requires-Dist: numpy
Requires-Dist: opencv-python
Requires-Dist: pandas
Requires-Dist: Pillow
Requires-Dist: pycocotools
Requires-Dist: scikit-learn
Requires-Dist: seaborn
Requires-Dist: tqdm
Requires-Dist: wget
